paka.webstatic-3.3.0-py3.5-nspkg.pth
paka/webstatic/__init__.py
paka/webstatic/cssmin.py
paka/webstatic/htmlmin.py
paka/webstatic/jsmin.py
paka/webstatic/manifest.py
paka/webstatic/pipeline.py
paka/webstatic/registry.py
paka.webstatic-3.3.0.dist-info/DESCRIPTION.rst
paka.webstatic-3.3.0.dist-info/METADATA
paka.webstatic-3.3.0.dist-info/RECORD
paka.webstatic-3.3.0.dist-info/WHEEL
paka.webstatic-3.3.0.dist-info/metadata.json
paka.webstatic-3.3.0.dist-info/namespace_packages.txt
paka.webstatic-3.3.0.dist-info/top_level.txt
