Metadata-Version: 2.0
Name: paka.webstatic
Version: 3.3.0
Summary: UNKNOWN
Home-page: https://github.com/PavloKapyshin/paka.webstatic
Author: Pavlo Kapyshin
Author-email: i@93z.org
License: BSD
Keywords: web css js html pipeline registry
Platform: UNKNOWN
Classifier: Development Status :: 4 - Beta
Classifier: Intended Audience :: Developers
Classifier: License :: OSI Approved :: BSD License
Classifier: Programming Language :: Python :: 2
Classifier: Programming Language :: Python :: 2.7
Classifier: Programming Language :: Python :: 3
Classifier: Programming Language :: Python :: 3.5
Classifier: Programming Language :: Python :: Implementation :: CPython
Classifier: Programming Language :: Python :: Implementation :: PyPy
Requires-Dist: six
Requires-Dist: markupsafe
Provides-Extra: testing
